vectorflow.py
vectorflow_ai-0.1.1.dist-info/LICENSE.md
vectorflow_ai-0.1.1.dist-info/METADATA
vectorflow_ai-0.1.1.dist-info/WHEEL
vectorflow_ai-0.1.1.dist-info/entry_points.txt
vectorflow_ai-0.1.1.dist-info/top_level.txt
vectorflow_ai-0.1.1.dist-info/RECORD
