Metadata-Version: 2.1
Name: vectorflow-ai
Version: 0.1.1
Summary: UNKNOWN
Home-page: UNKNOWN
License: UNKNOWN
Platform: UNKNOWN
License-File: LICENSE.md
